MANIFEST.in
README
autotranslate.py
gtrans.py
langs.yml
setup.py
auto_translator.egg-info/PKG-INFO
auto_translator.egg-info/SOURCES.txt
auto_translator.egg-info/dependency_links.txt
auto_translator.egg-info/requires.txt
auto_translator.egg-info/top_level.txt